{
  "title": "ModuleConfig",
  "description": "A class to hold the type and configuration for a module instance.",
  "type": "object",
  "properties": {
    "module_type": {
      "title": "Module Type",
      "description": "The module type.",
      "type": "string"
    },
    "module_config": {
      "title": "Module Config",
      "description": "The configuration for the module.",
      "type": "object"
    },
    "doc": {
      "title": "Doc",
      "description": "Documentation for this operation.",
      "allOf": [
        {
          "$ref": "#/definitions/DocumentationMetadataModel"
        }
      ]
    }
  },
  "required": [
    "module_type"
  ],
  "additionalProperties": false,
  "definitions": {
    "DocumentationMetadataModel": {
      "title": "DocumentationMetadataModel",
      "description": "Base class for classes that represent value metadata in kiara.",
      "type": "object",
      "properties": {
        "description": {
          "title": "Description",
          "description": "Short description of the item.",
          "default": "-- n/a --",
          "type": "string"
        },
        "doc": {
          "title": "Doc",
          "description": "Detailed documentation of the item (in markdown).",
          "type": "string"
        }
      }
    }
  }
}